peng/__init__.py
peng/constants.py
peng/functions.py
peng/pkgdata.py
peng/ptypes.py
peng/touchstone.py
peng/wave_core.py
peng/wave_functions.py
peng-1.0.11.dist-info/AUTHORS.rst
peng-1.0.11.dist-info/LICENSE
peng-1.0.11.dist-info/METADATA
peng-1.0.11.dist-info/WHEEL
peng-1.0.11.dist-info/top_level.txt
peng-1.0.11.dist-info/RECORD
